mock.py
auto_test_mock_server-1.0.1.dist-info/METADATA
auto_test_mock_server-1.0.1.dist-info/WHEEL
auto_test_mock_server-1.0.1.dist-info/top_level.txt
auto_test_mock_server-1.0.1.dist-info/RECORD
