Metadata-Version: 2.1
Name: auto-test-mock-server
Version: 1.0.1
Summary: In order to solve the interface dependence of interface test
Home-page: https://github.com/test
Author: zhujiahuan
Author-email: zhujiahuan@yfcloud.com
License: MIT
Platform: UNKNOWN
